aru_metadata_parser/__init__.py
aru_metadata_parser/parse.py
aru_metadata_parser/utils.py
aru_metadata_parser-0.1.0.dist-info/LICENSE
aru_metadata_parser-0.1.0.dist-info/METADATA
aru_metadata_parser-0.1.0.dist-info/WHEEL
aru_metadata_parser-0.1.0.dist-info/entry_points.txt
aru_metadata_parser-0.1.0.dist-info/RECORD
