Metadata-Version: 2.1
Name: aru-metadata-parser
Version: 0.1.0
Summary: Parse metadata from ARUs including the AudioMoth
Home-page: https://github.com/jkitzes/aru_metadata_parser
License: MIT
Author: Sam Lapp
Author-email: sammlapp@gmail.com
Requires-Python: >=3.8
Classifier: License :: OSI Approved :: MIT License
Classifier: Programming Language :: Python :: 3
Classifier: Programming Language :: Python :: 3.8
Classifier: Programming Language :: Python :: 3.9
Classifier: Programming Language :: Python :: 3.10
Classifier: Programming Language :: Python :: 3.11
Requires-Dist: docopt (>=0.6.2)
Requires-Dist: pytz (>=2015.7)
Requires-Dist: soundfile (>=0.11)
Project-URL: Repository, https://github.com/jkitzes/aru_metadata_parser
